{
  "kind": "collectionType",
  "collectionName": "lokasi_pahangs",
  "info": {
    "singularName": "lokasi-pahang",
    "pluralName": "lokasi-pahangs",
    "displayName": "LokasiPahang"
  },
  "options": {
    "draftAndPublish": true
  },
  "pluginOptions": {},
  "attributes": {
    "Title": {
      "type": "string"
    },
    "BackgroundImage": {
      "allowedTypes": [
        "images"
      ],
      "type": "media",
      "multiple": false
    },
    "Icon": {
      "allowedTypes": [
        "images"
      ],
      "type": "media",
      "multiple": false
    },
    "Location": {
      "type": "string"
    },
    "PhoneNo": {
      "type": "string"
    },
    "FaxNo": {
      "type": "string"
    },
    "OperationTime": {
      "type": "text"
    }
  }
}
